vist/__init__.py
vist/common/__init__.py
vist/common/registry.py
vist/common/bbox/__init__.py
vist/common/bbox/utils.py
vist/common/bbox/matchers/__init__.py
vist/common/bbox/matchers/base.py
vist/common/bbox/matchers/max_iou.py
vist/common/bbox/matchers/max_iou_test.py
vist/common/bbox/poolers/__init__.py
vist/common/bbox/poolers/base.py
vist/common/bbox/poolers/d2_roi_pooler.py
vist/common/bbox/samplers/__init__.py
vist/common/bbox/samplers/base.py
vist/common/bbox/samplers/combined.py
vist/common/bbox/samplers/combined_test.py
vist/common/bbox/samplers/random.py
vist/common/bbox/samplers/random_test.py
vist/common/bbox/samplers/utils.py
vist/common/io/__init__.py
vist/common/io/backend_test.py
vist/common/io/base.py
vist/common/io/file.py
vist/common/io/hdf5.py
vist/common/utils/__init__.py
vist/common/utils/parallel.py
vist/common/utils/time.py
vist/config/__init__.py
vist/config/config.py
vist/config/config_test.py
vist/config/defaults.py
vist/config/defaults_test.py
vist/data/__init__.py
vist/data/build.py
vist/data/build_test.py
vist/data/dataset_mapper.py
vist/data/dataset_mapper_test.py
vist/data/samplers.py
vist/data/utils.py
vist/data/datasets/__init__.py
vist/data/datasets/base.py
vist/data/datasets/bdd100k.py
vist/data/datasets/coco.py
vist/data/datasets/custom.py
vist/data/datasets/kitti.py
vist/data/datasets/motchallenge.py
vist/data/datasets/scalabel.py
vist/data/datasets/waymo.py
vist/data/transforms/__init__.py
vist/data/transforms/augmentations.py
vist/data/transforms/base.py
vist/engine/__init__.py
vist/engine/evaluator.py
vist/engine/trainer.py
vist/engine/trainer_test.py
vist/engine/utils.py
vist/engine/utils_test.py
vist/model/__init__.py
vist/model/base.py
vist/model/quasi_dense_rcnn.py
vist/model/detect/__init__.py
vist/model/detect/base.py
vist/model/detect/d2_utils.py
vist/model/detect/d2_utils_test.py
vist/model/detect/d2_wrapper.py
vist/model/detect/mmdet_utils.py
vist/model/detect/mmdet_wrapper.py
vist/model/track/__init__.py
vist-0.0.dist-info/LICENSE
vist-0.0.dist-info/METADATA
vist-0.0.dist-info/WHEEL
vist-0.0.dist-info/top_level.txt
vist-0.0.dist-info/RECORD
