Metadata-Version: 2.1
Name: vist
Version: 0.0
Summary: VisT Python Package for perception and motion understanding
Home-page: https://cv.ethz.ch/
Author: CVL @ ETHZ
Author-email: i@yf.io
License: UNKNOWN
Project-URL: Documentation, https://github.com/syscv/
Project-URL: Source, https://github.com/syscv/
Project-URL: Tracker, https://github.com/syscv/
Platform: UNKNOWN
Classifier: Programming Language :: Python :: 3
Classifier: License :: OSI Approved :: BSD License
Classifier: Operating System :: OS Independent
Requires-Python: >=3.7
License-File: LICENSE
Requires-Dist: numpy
Requires-Dist: Pillow
Requires-Dist: plyfile
Requires-Dist: psutil
Requires-Dist: pycocotools
Requires-Dist: pydantic
Requires-Dist: pytoml
Requires-Dist: PyYAML
Requires-Dist: requests
Requires-Dist: scalabel
Requires-Dist: torch
Requires-Dist: torchvision
Requires-Dist: tqdm
Requires-Dist: devtools
